huizhi_coupon_lengyue1084/__init__.py
huizhi_coupon_lengyue1084/__main__.py
huizhi_coupon_lengyue1084/cache.py
huizhi_coupon_lengyue1084/server.py
huizhi_coupon_lengyue1084-0.1.18.dist-info/METADATA
huizhi_coupon_lengyue1084-0.1.18.dist-info/WHEEL
huizhi_coupon_lengyue1084-0.1.18.dist-info/entry_points.txt
huizhi_coupon_lengyue1084-0.1.18.dist-info/licenses/LICENSE
huizhi_coupon_lengyue1084-0.1.18.dist-info/RECORD
