Metadata-Version: 2.4
Name: huizhi-coupon-lengyue1084
Version: 0.1.18
Summary: Agentsyun优惠券MCP服务，提供多品类优惠券查询、筛选和推广链接生成功能，支持外卖、美食、休闲娱乐、酒店民宿、门票度假、医药等多个类目
Author-email: lengyue1084 <95695864@qq.com>
License: Copyright (c) 2018 The Python Packaging Authority
License-File: LICENSE
Requires-Python: >=3.12
Requires-Dist: annotated>=0.0.2
Requires-Dist: mcp
Requires-Dist: requests>=2.32.5
